{
    "team_name": "User's Team",
    "overall_rating": 85,
    "players": [
      {
        "name": "John Smith",
        "position": "QB",
        "stats": {
          "speed": 85,
          "strength": 70,
          "agility": 80,
          "accuracy": 95,
          "awareness": 90
        },
        "salary": 125000000
      },
      {
        "name": "Mike Johnson",
        "position": "RB",
        "stats": {
          "speed": 92,
          "strength": 85,
          "agility": 90,
          "elusiveness": 95,
          "vision": 88
        },
        "salary": 18000000
      },
      {
        "name": "Chris Davis",
        "position": "WR",
        "stats": {
          "speed": 94,
          "strength": 75,
          "agility": 92,
          "catching": 96,
          "route_running": 90
        },
        "salary": 20000000
      },
      {
        "name": "Alex Brown",
        "position": "TE",
        "stats": {
          "speed": 78,
          "strength": 85,
          "agility": 75,
          "catching": 82,
          "blocking": 80
        },
        "salary": 1500000
      },
      {
        "name": "Ryan Miller",
        "position": "OT",
        "stats": {
          "strength": 90,
          "agility": 60,
          "pass_block": 78,
          "run_block": 82,
          "awareness": 75
        },
        "salary": 1200000
      },
      {
        "name": "Ethan Wilson",
        "position": "OG",
        "stats": {
          "strength": 88,
          "agility": 65,
          "pass_block": 80,
          "run_block": 85,
          "awareness": 78
        },
        "salary": 1100000
      },
      {
        "name": "Daniel Harris",
        "position": "C",
        "stats": {
          "strength": 85,
          "agility": 70,
          "pass_block": 82,
          "run_block": 84,
          "awareness": 80
        },
        "salary": 1000000
      },
      {
        "name": "Kevin Lee",
        "position": "DE",
        "stats": {
          "speed": 85,
          "strength": 90,
          "agility": 80,
          "pass_rush": 88,
          "run_stop": 85
        },
        "salary": 2200000
      },
      {
        "name": "Brian Taylor",
        "position": "DT",
        "stats": {
          "speed": 70,
          "strength": 92,
          "agility": 65,
          "pass_rush": 75,
          "run_stop": 88
        },
        "salary": 1900000
      },
      {
        "name": "Jason White",
        "position": "LB",
        "stats": {
          "speed": 85,
          "strength": 88,
          "agility": 80,
          "tackling": 90,
          "coverage": 75
        },
        "salary": 1700000
      },
      {
        "name": "Marcus Green",
        "position": "CB",
        "stats": {
          "speed": 90,
          "strength": 70,
          "agility": 88,
          "man_coverage": 85,
          "zone_coverage": 80
        },
        "salary": 1600000
      },
      {
        "name": "Tyler Evans",
        "position": "S",
        "stats": {
          "speed": 85,
          "strength": 75,
          "agility": 80,
          "tackling": 82,
          "coverage": 78
        },
        "salary": 1400000
      },
      {
        "name": "Logan Brown",
        "position": "K",
        "stats": {
          "power": 90,
          "accuracy": 85,
          "clutch": 80
        },
        "salary": 800000
      },
      {
        "name": "Derek Carter",
        "position": "P",
        "stats": {
          "power": 88,
          "accuracy": 82,
          "hang_time": 85
        },
        "salary": 7000000
      }
    ]
  }